{
    "module": "compression",
    "template": "module-function",
    "differences": [
        {
            "code": "export-assignment-is-different",
            "exportAssignmentExpected": "compression",
            "exportAssignmentActual": "Compression"
        },
        {
            "code": "missing-parameter",
            "parameterMissing": {
                "name": "chunkSize",
                "type": {
                    "kind": "primitive_keyword",
                    "value": "number"
                },
                "optional": true,
                "modifiers": [],
                "dotDotDotToken": false
            }
        },
        {
            "code": "missing-parameter",
            "parameterMissing": {
                "name": "level",
                "type": {
                    "kind": "primitive_keyword",
                    "value": "number"
                },
                "optional": true,
                "modifiers": [],
                "dotDotDotToken": false
            }
        },
        {
            "code": "missing-parameter",
            "parameterMissing": {
                "name": "memLevel",
                "type": {
                    "kind": "primitive_keyword",
                    "value": "number"
                },
                "optional": true,
                "modifiers": [],
                "dotDotDotToken": false
            }
        },
        {
            "code": "missing-parameter",
            "parameterMissing": {
                "name": "strategy",
                "type": {
                    "kind": "primitive_keyword",
                    "value": "number"
                },
                "optional": true,
                "modifiers": [],
                "dotDotDotToken": false
            }
        },
        {
            "code": "type-non-empty-intersection",
            "parameterExpected": {
                "name": "threshold",
                "type": {
                    "kind": "union_type",
                    "value": [
                        {
                            "kind": "primitive_keyword",
                            "value": "number"
                        },
                        {
                            "kind": "primitive_keyword",
                            "value": "string"
                        },
                        {
                            "kind": "undefined_keyword",
                            "value": "undefined"
                        }
                    ]
                },
                "optional": true,
                "modifiers": [],
                "dotDotDotToken": false
            },
            "parameterActual": {
                "name": "threshold",
                "type": {
                    "kind": "primitive_keyword",
                    "value": "number"
                },
                "optional": false,
                "modifiers": [],
                "dotDotDotToken": false
            }
        },
        {
            "code": "missing-parameter",
            "parameterMissing": {
                "name": "windowBits",
                "type": {
                    "kind": "primitive_keyword",
                    "value": "number"
                },
                "optional": true,
                "modifiers": [],
                "dotDotDotToken": false
            }
        }
    ],
    "tags": [
        "void",
        "optional-parameter",
        "number",
        "call-signature",
        "boolean",
        "string",
        "type-union",
        "index-signature",
        "type-any"
    ]
}
