{
    "module": "passport-steam",
    "template": "module-function",
    "differences": [
        {
            "code": "export-assignment-is-different",
            "exportAssignmentExpected": "passport_steam",
            "exportAssignmentActual": "PassportSteam"
        },
        {
            "code": "type-non-empty-intersection",
            "parameterExpected": {
                "name": "options",
                "type": {
                    "kind": "any_keyword",
                    "value": "any"
                },
                "optional": false,
                "modifiers": [],
                "dotDotDotToken": false
            },
            "parameterActual": {
                "name": "thePath",
                "type": {
                    "kind": "primitive_keyword",
                    "value": "string"
                },
                "optional": false,
                "modifiers": [],
                "dotDotDotToken": false
            }
        },
        {
            "code": "type-non-empty-intersection",
            "parameterExpected": {
                "name": "validate",
                "type": {
                    "kind": "any_keyword",
                    "value": "any"
                },
                "optional": false,
                "modifiers": [],
                "dotDotDotToken": false
            },
            "parameterActual": {
                "name": "potentialParent",
                "type": {
                    "kind": "primitive_keyword",
                    "value": "string"
                },
                "optional": false,
                "modifiers": [],
                "dotDotDotToken": false
            }
        }
    ],
    "tags": [
        "type-any"
    ]
}
